jsonpath_ng/__init__.py
jsonpath_ng/exceptions.py
jsonpath_ng/jsonpath.py
jsonpath_ng/lexer.py
jsonpath_ng/parser.py
jsonpath_ng/bin/__init__.py
jsonpath_ng/bin/jsonpath.py
jsonpath_ng/ext/__init__.py
jsonpath_ng/ext/arithmetic.py
jsonpath_ng/ext/filter.py
jsonpath_ng/ext/iterable.py
jsonpath_ng/ext/parser.py
jsonpath_ng/ext/string.py
jsonpath_ng_aerospike-1.5.3.dist-info/LICENSE
jsonpath_ng_aerospike-1.5.3.dist-info/METADATA
jsonpath_ng_aerospike-1.5.3.dist-info/NOTICE
jsonpath_ng_aerospike-1.5.3.dist-info/WHEEL
jsonpath_ng_aerospike-1.5.3.dist-info/entry_points.txt
jsonpath_ng_aerospike-1.5.3.dist-info/top_level.txt
jsonpath_ng_aerospike-1.5.3.dist-info/RECORD
