Metadata-Version: 2.1
Name: jsonpath-ng-aerospike
Version: 1.5.3
Summary: A final implementation of JSONPath for Python that aims to be standard compliant, including arithmetic and binary comparison operators and providing clear AST for metaprogramming.
Home-page: https://github.com/aerospike-community/jsonpath-ng
Author: Tomas Aparicio, Julian Nguyen
Author-email: tomas@aparicio.me, jnguyen@aerospike.com
License: Apache 2.0
Classifier: Development Status :: 5 - Production/Stable
Classifier: Intended Audience :: Developers
Classifier: License :: OSI Approved :: Apache Software License
Classifier: Programming Language :: Python :: 2.7
Classifier: Programming Language :: Python :: 3
Classifier: Programming Language :: Python :: 3.5
Classifier: Programming Language :: Python :: 3.6
Classifier: Programming Language :: Python :: 3.7
Classifier: Programming Language :: Python :: 3.8
License-File: LICENSE
License-File: NOTICE
Requires-Dist: ply
Requires-Dist: decorator
Requires-Dist: six
